{
    "backend": "api-server-django",
    "db_name": "",
    "db_pass": "",
    "db_type": "sqlite",
    "db_user": "",
    "dbms": "1",
    "description": "generated product",
    "design": "material-kit",
    "docker": "1",
    "err_code": 0,
    "frontend": "react",
    "heroku": "0",
    "pattern": "fullstack",
    "pro": "0",
    "task_id": "f425289b-c1ef-4188-8b02-7d9e108ebad4",
    "task_info": "Upload Sources [0%] - 347 files",
    "task_output": "f425289b-c1ef-4188-8b02-7d9e108ebad4.zip",
    "task_result": "SUCCESS",
    "task_state": "RUNNING",
    "task_ts_end": "2023-07-08-18-48-01",
    "task_ts_start": "2023-07-08-18-47-58"
}